{
  "gameweek": 8,
  "timestamp": "2025-10-17T10:07:42.885011",
  "mode": "fresh_start",
  "availability_issues": [],
  "squad_selection": {
    "squad": {
      "GKP": [
        {
          "id": 470,
          "name": "D\u00fabravka",
          "team": "BUR",
          "position": "GKP",
          "price": 4.0,
          "form": 3.0,
          "points_per_game": 3.0,
          "dc_per_90": 0.0,
          "is_dc_specialist": false,
          "total_points": 18,
          "minutes": 540,
          "value_score": 0.75,
          "dc_consistency_pct": 0.0
        },
        {
          "id": 341,
          "name": "Darlow",
          "team": "LEE",
          "position": "GKP",
          "price": 4.0,
          "form": 2.25,
          "points_per_game": 2.25,
          "dc_per_90": 0.0,
          "is_dc_specialist": false,
          "total_points": 9,
          "minutes": 360,
          "value_score": 0.5625,
          "dc_consistency_pct": 0.0
        }
      ],
      "DEF": [
        {
          "id": 260,
          "name": "Gu\u00e9hi",
          "team": "CRY",
          "position": "DEF",
          "price": 4.9,
          "form": 7.166666666666667,
          "points_per_game": 7.166666666666667,
          "dc_per_90": 7.833333333333333,
          "is_dc_specialist": true,
          "total_points": 43,
          "minutes": 540,
          "value_score": 1.4625850340136053,
          "dc_consistency_pct": 100.0
        },
        {
          "id": 694,
          "name": "Mukiele",
          "team": "SUN",
          "position": "DEF",
          "price": 4.0,
          "form": 5.4,
          "points_per_game": 5.4,
          "dc_per_90": 12.6,
          "is_dc_specialist": true,
          "total_points": 27,
          "minutes": 450,
          "value_score": 1.35,
          "dc_consistency_pct": 100.0
        },
        {
          "id": 72,
          "name": "Senesi",
          "team": "BOU",
          "position": "DEF",
          "price": 5.0,
          "form": 6.571428571428571,
          "points_per_game": 6.571428571428571,
          "dc_per_90": 12.571428571428571,
          "is_dc_specialist": true,
          "total_points": 46,
          "minutes": 617,
          "value_score": 1.3142857142857143,
          "dc_consistency_pct": 100.0
        },
        {
          "id": 636,
          "name": "S.Bueno",
          "team": "WOL",
          "position": "DEF",
          "price": 4.4,
          "form": 5.333333333333333,
          "points_per_game": 5.333333333333333,
          "dc_per_90": 9.666666666666666,
          "is_dc_specialist": true,
          "total_points": 16,
          "minutes": 214,
          "value_score": 1.212121212121212,
          "dc_consistency_pct": 100.0
        },
        {
          "id": 8,
          "name": "J.Timber",
          "team": "ARS",
          "position": "DEF",
          "price": 5.9,
          "form": 6.857142857142857,
          "points_per_game": 6.857142857142857,
          "dc_per_90": 6.428571428571429,
          "is_dc_specialist": true,
          "total_points": 48,
          "minutes": 521,
          "value_score": 1.162227602905569,
          "dc_consistency_pct": 100.0
        }
      ],
      "MID": [
        {
          "id": 82,
          "name": "Semenyo",
          "team": "BOU",
          "position": "MID",
          "price": 7.9,
          "form": 9.428571428571429,
          "points_per_game": 9.428571428571429,
          "dc_per_90": 8.285714285714286,
          "is_dc_specialist": true,
          "total_points": 66,
          "minutes": 630,
          "value_score": 1.193490054249548,
          "dc_consistency_pct": 100.0
        },
        {
          "id": 267,
          "name": "Sarr",
          "team": "CRY",
          "position": "MID",
          "price": 6.5,
          "form": 7.25,
          "points_per_game": 7.25,
          "dc_per_90": 5.5,
          "is_dc_specialist": true,
          "total_points": 29,
          "minutes": 344,
          "value_score": 1.1153846153846154,
          "dc_consistency_pct": 100.0
        },
        {
          "id": 241,
          "name": "Caicedo",
          "team": "CHE",
          "position": "MID",
          "price": 5.8,
          "form": 6.428571428571429,
          "points_per_game": 6.428571428571429,
          "dc_per_90": 13.714285714285714,
          "is_dc_specialist": true,
          "total_points": 45,
          "minutes": 630,
          "value_score": 1.1083743842364533,
          "dc_consistency_pct": 100.0
        },
        {
          "id": 390,
          "name": "Gravenberch",
          "team": "LIV",
          "position": "MID",
          "price": 5.7,
          "form": 6.166666666666667,
          "points_per_game": 6.166666666666667,
          "dc_per_90": 9.333333333333334,
          "is_dc_specialist": true,
          "total_points": 37,
          "minutes": 540,
          "value_score": 1.0818713450292399,
          "dc_consistency_pct": 100.0
        },
        {
          "id": 303,
          "name": "Garner",
          "team": "EVE",
          "position": "MID",
          "price": 5.0,
          "form": 5.333333333333333,
          "points_per_game": 5.333333333333333,
          "dc_per_90": 12.166666666666666,
          "is_dc_specialist": true,
          "total_points": 32,
          "minutes": 540,
          "value_score": 1.0666666666666667,
          "dc_consistency_pct": 100.0
        }
      ],
      "FWD": [
        {
          "id": 430,
          "name": "Haaland",
          "team": "MCI",
          "position": "FWD",
          "price": 14.5,
          "form": 10.333333333333334,
          "points_per_game": 10.333333333333334,
          "dc_per_90": 4.0,
          "is_dc_specialist": true,
          "total_points": 62,
          "minutes": 503,
          "value_score": 0.7126436781609196,
          "dc_consistency_pct": 100.0
        },
        {
          "id": 714,
          "name": "Woltemade",
          "team": "NEW",
          "position": "FWD",
          "price": 7.2,
          "form": 6.0,
          "points_per_game": 6.0,
          "dc_per_90": 3.3333333333333335,
          "is_dc_specialist": true,
          "total_points": 18,
          "minutes": 213,
          "value_score": 0.8333333333333333,
          "dc_consistency_pct": 100.0
        },
        {
          "id": 136,
          "name": "Thiago",
          "team": "BRE",
          "position": "FWD",
          "price": 6.1,
          "form": 5.0,
          "points_per_game": 5.0,
          "dc_per_90": 4.666666666666667,
          "is_dc_specialist": true,
          "total_points": 30,
          "minutes": 494,
          "value_score": 0.819672131147541,
          "dc_consistency_pct": 100.0
        }
      ]
    },
    "total_cost": 90.89999999999999,
    "remaining_budget": 9.100000000000009,
    "dc_count": 13
  },
  "captain": {
    "captain": {
      "id": 430,
      "name": "Haaland",
      "team": "MCI",
      "position": "FWD",
      "price": 14.5,
      "form": 10.333333333333334,
      "points_per_game": 10.333333333333334,
      "dc_per_90": 4.0,
      "is_dc_specialist": true,
      "total_points": 62,
      "minutes": 503,
      "value_score": 0.7126436781609196,
      "dc_consistency_pct": 100.0
    },
    "vice_captain": {
      "id": 82,
      "name": "Semenyo",
      "team": "BOU",
      "position": "MID",
      "price": 7.9,
      "form": 9.428571428571429,
      "points_per_game": 9.428571428571429,
      "dc_per_90": 8.285714285714286,
      "is_dc_specialist": true,
      "total_points": 66,
      "minutes": 630,
      "value_score": 1.193490054249548,
      "dc_consistency_pct": 100.0
    }
  },
  "formation": {
    "starting_xi": {
      "GKP": [
        {
          "id": 470,
          "name": "D\u00fabravka",
          "team": "BUR",
          "position": "GKP",
          "price": 4.0,
          "form": 3.0,
          "points_per_game": 3.0,
          "dc_per_90": 0.0,
          "is_dc_specialist": false,
          "total_points": 18,
          "minutes": 540,
          "value_score": 0.75,
          "dc_consistency_pct": 0.0
        }
      ],
      "DEF": [
        {
          "id": 260,
          "name": "Gu\u00e9hi",
          "team": "CRY",
          "position": "DEF",
          "price": 4.9,
          "form": 7.166666666666667,
          "points_per_game": 7.166666666666667,
          "dc_per_90": 7.833333333333333,
          "is_dc_specialist": true,
          "total_points": 43,
          "minutes": 540,
          "value_score": 1.4625850340136053,
          "dc_consistency_pct": 100.0
        },
        {
          "id": 694,
          "name": "Mukiele",
          "team": "SUN",
          "position": "DEF",
          "price": 4.0,
          "form": 5.4,
          "points_per_game": 5.4,
          "dc_per_90": 12.6,
          "is_dc_specialist": true,
          "total_points": 27,
          "minutes": 450,
          "value_score": 1.35,
          "dc_consistency_pct": 100.0
        },
        {
          "id": 72,
          "name": "Senesi",
          "team": "BOU",
          "position": "DEF",
          "price": 5.0,
          "form": 6.571428571428571,
          "points_per_game": 6.571428571428571,
          "dc_per_90": 12.571428571428571,
          "is_dc_specialist": true,
          "total_points": 46,
          "minutes": 617,
          "value_score": 1.3142857142857143,
          "dc_consistency_pct": 100.0
        }
      ],
      "MID": [
        {
          "id": 82,
          "name": "Semenyo",
          "team": "BOU",
          "position": "MID",
          "price": 7.9,
          "form": 9.428571428571429,
          "points_per_game": 9.428571428571429,
          "dc_per_90": 8.285714285714286,
          "is_dc_specialist": true,
          "total_points": 66,
          "minutes": 630,
          "value_score": 1.193490054249548,
          "dc_consistency_pct": 100.0
        },
        {
          "id": 267,
          "name": "Sarr",
          "team": "CRY",
          "position": "MID",
          "price": 6.5,
          "form": 7.25,
          "points_per_game": 7.25,
          "dc_per_90": 5.5,
          "is_dc_specialist": true,
          "total_points": 29,
          "minutes": 344,
          "value_score": 1.1153846153846154,
          "dc_consistency_pct": 100.0
        },
        {
          "id": 241,
          "name": "Caicedo",
          "team": "CHE",
          "position": "MID",
          "price": 5.8,
          "form": 6.428571428571429,
          "points_per_game": 6.428571428571429,
          "dc_per_90": 13.714285714285714,
          "is_dc_specialist": true,
          "total_points": 45,
          "minutes": 630,
          "value_score": 1.1083743842364533,
          "dc_consistency_pct": 100.0
        },
        {
          "id": 390,
          "name": "Gravenberch",
          "team": "LIV",
          "position": "MID",
          "price": 5.7,
          "form": 6.166666666666667,
          "points_per_game": 6.166666666666667,
          "dc_per_90": 9.333333333333334,
          "is_dc_specialist": true,
          "total_points": 37,
          "minutes": 540,
          "value_score": 1.0818713450292399,
          "dc_consistency_pct": 100.0
        },
        {
          "id": 303,
          "name": "Garner",
          "team": "EVE",
          "position": "MID",
          "price": 5.0,
          "form": 5.333333333333333,
          "points_per_game": 5.333333333333333,
          "dc_per_90": 12.166666666666666,
          "is_dc_specialist": true,
          "total_points": 32,
          "minutes": 540,
          "value_score": 1.0666666666666667,
          "dc_consistency_pct": 100.0
        }
      ],
      "FWD": [
        {
          "id": 430,
          "name": "Haaland",
          "team": "MCI",
          "position": "FWD",
          "price": 14.5,
          "form": 10.333333333333334,
          "points_per_game": 10.333333333333334,
          "dc_per_90": 4.0,
          "is_dc_specialist": true,
          "total_points": 62,
          "minutes": 503,
          "value_score": 0.7126436781609196,
          "dc_consistency_pct": 100.0
        },
        {
          "id": 714,
          "name": "Woltemade",
          "team": "NEW",
          "position": "FWD",
          "price": 7.2,
          "form": 6.0,
          "points_per_game": 6.0,
          "dc_per_90": 3.3333333333333335,
          "is_dc_specialist": true,
          "total_points": 18,
          "minutes": 213,
          "value_score": 0.8333333333333333,
          "dc_consistency_pct": 100.0
        }
      ]
    },
    "bench": [
      {
        "id": 341,
        "name": "Darlow",
        "team": "LEE",
        "position": "GKP",
        "price": 4.0,
        "form": 2.25,
        "points_per_game": 2.25,
        "dc_per_90": 0.0,
        "is_dc_specialist": false,
        "total_points": 9,
        "minutes": 360,
        "value_score": 0.5625,
        "dc_consistency_pct": 0.0
      },
      {
        "id": 636,
        "name": "S.Bueno",
        "team": "WOL",
        "position": "DEF",
        "price": 4.4,
        "form": 5.333333333333333,
        "points_per_game": 5.333333333333333,
        "dc_per_90": 9.666666666666666,
        "is_dc_specialist": true,
        "total_points": 16,
        "minutes": 214,
        "value_score": 1.212121212121212,
        "dc_consistency_pct": 100.0
      },
      {
        "id": 8,
        "name": "J.Timber",
        "team": "ARS",
        "position": "DEF",
        "price": 5.9,
        "form": 6.857142857142857,
        "points_per_game": 6.857142857142857,
        "dc_per_90": 6.428571428571429,
        "is_dc_specialist": true,
        "total_points": 48,
        "minutes": 521,
        "value_score": 1.162227602905569,
        "dc_consistency_pct": 100.0
      },
      {
        "id": 136,
        "name": "Thiago",
        "team": "BRE",
        "position": "FWD",
        "price": 6.1,
        "form": 5.0,
        "points_per_game": 5.0,
        "dc_per_90": 4.666666666666667,
        "is_dc_specialist": true,
        "total_points": 30,
        "minutes": 494,
        "value_score": 0.819672131147541,
        "dc_consistency_pct": 100.0
      }
    ],
    "formation": "3-5-2"
  }
}